odoo/addons/storage_image_product_brand_import/README.rst
odoo/addons/storage_image_product_brand_import/__init__.py
odoo/addons/storage_image_product_brand_import/__manifest__.py
odoo/addons/storage_image_product_brand_import/i18n/storage_image_product_brand_import.pot
odoo/addons/storage_image_product_brand_import/models/__init__.py
odoo/addons/storage_image_product_brand_import/models/product_brand_image_relation.py
odoo/addons/storage_image_product_brand_import/readme/CONTRIBUTORS.rst
odoo/addons/storage_image_product_brand_import/readme/DESCRIPTION.rst
odoo/addons/storage_image_product_brand_import/readme/USAGE.rst
odoo/addons/storage_image_product_brand_import/static/description/icon.png
odoo/addons/storage_image_product_brand_import/static/description/index.html
odoo14_addon_storage_image_product_brand_import-14.0.1.0.1.dist-info/METADATA
odoo14_addon_storage_image_product_brand_import-14.0.1.0.1.dist-info/WHEEL
odoo14_addon_storage_image_product_brand_import-14.0.1.0.1.dist-info/top_level.txt
odoo14_addon_storage_image_product_brand_import-14.0.1.0.1.dist-info/RECORD
